Metadata-Version: 2.1
Name: StataLovers
Version: 1.3
Summary: Stata-like functions tab and summarize
Home-page: UNKNOWN
Author: Mila Kolpashnikova
Author-email: kamilakolpashnikova@gmail.com
License: UNKNOWN
Platform: UNKNOWN
